[
  {
    "variation": "default-slice",
    "name": "Default slice",
    "slice_type": "project_card",
    "items": [],
    "primary": {
      "title": [
        {
          "type": "heading1",
          "text": "Strategize bricks-and-clicks markets",
          "spans": []
        }
      ],
      "projectImage": {
        "dimensions": {
          "width": 900,
          "height": 500
        },
        "alt": "Placeholder image",
        "copyright": null,
        "url": "https://images.unsplash.com/photo-1531771686035-25f47595c87a?w=900&h=500&fit=crop"
      },
      "project": {
        "link_type": "Web",
        "url": "http://twitter.com"
      }
    }
  }
]